{
  "gender": {
    "female_stereotypes": [
      "emotional",
      "nurturing",
      "caring",
      "empathetic",
      "weak",
      "submissive",
      "passive",
      "gentle",
      "sensitive",
      "delicate",
      "fragile",
      "dependent",
      "indecisive",
      "irrational",
      "gossipy",
      "dramatic",
      "hysterical",
      "petite",
      "dainty",
      "soft-spoken"
    ],
    "male_stereotypes": [
      "aggressive",
      "strong",
      "rational",
      "logical",
      "dominant",
      "assertive",
      "confident",
      "independent",
      "competitive",
      "ambitious",
      "authoritative",
      "decisive",
      "analytical",
      "stoic",
      "unemotional",
      "tough",
      "brave",
      "protective",
      "mechanical",
      "technical"
    ],
    "patterns": [
      "woman driver",
      "male nurse",
      "female doctor",
      "male secretary",
      "working mother",
      "career woman",
      "house husband",
      "stay-at-home dad",
      "bossy woman",
      "emotional female",
      "typical woman",
      "typical man",
      "acts like a girl",
      "man up",
      "be a man"
    ]
  },
  "racial": {
    "patterns": [
      "exotic",
      "articulate",
      "well-spoken",
      "urban",
      "inner city",
      "thug",
      "ghetto",
      "sketchy neighbourhood",
      "bad neighbourhood",
      "dangerous area",
      "foreign",
      "foreigner",
      "where are you really from",
      "you speak English well",
      "terrorist",
      "illegal",
      "immigrant",
      "model minority"
    ],
    "descriptors": [
      "exotic",
      "ethnic",
      "oriental",
      "coloured",
      "primitive",
      "tribal",
      "savage",
      "uncivilised",
      "third world",
      "developing",
      "backward",
      "uneducated",
      "poor",
      "dirty",
      "criminal",
      "violent",
      "lazy",
      "hardworking immigrant"
    ]
  },
  "age": {
    "young_stereotypes": [
      "tech-savvy",
      "lazy",
      "entitled",
      "snowflake",
      "naive",
      "immature",
      "irresponsible",
      "inexperienced",
      "unprofessional",
      "knows nothing",
      "too young",
      "fresh-faced",
      "millennial",
      "gen z",
      "kids these days",
      "young and dumb"
    ],
    "old_stereotypes": [
      "technophobic",
      "forgetful",
      "slow",
      "out of touch",
      "old-fashioned",
      "senile",
      "frail",
      "elderly",
      "past their prime",
      "over the hill",
      "outdated",
      "stuck in their ways",
      "resistant to change",
      "confused",
      "hard of hearing",
      "wise",
      "experienced elder"
    ],
    "patterns": [
      "too old for",
      "too young for",
      "act your age",
      "young and energetic",
      "old and wise",
      "millennial entitlement",
      "boomer mentality",
      "old timer",
      "youngster",
      "senior moment"
    ]
  },
  "professional": {
    "occupation_gender_pairs": [
      ["engineer", "male"],
      ["nurse", "female"],
      ["teacher", "female"],
      ["CEO", "male"],
      ["secretary", "female"],
      ["doctor", "male"],
      ["pilot", "male"],
      ["flight attendant", "female"],
      ["mechanic", "male"],
      ["hairdresser", "female"],
      ["construction worker", "male"],
      ["childcare worker", "female"],
      ["firefighter", "male"],
      ["librarian", "female"],
      ["surgeon", "male"],
      ["receptionist", "female"]
    ],
    "patterns": [
      "surprisingly competent",
      "naturally good at",
      "lacks technical skills",
      "not suited for",
      "perfect job for a",
      "typical career for",
      "unusual profession for",
      "rare to see a",
      "doesn't look like a",
      "hard to believe they're a"
    ],
    "stereotypical_traits": {
      "leadership": ["male", "authoritative", "decisive", "commanding"],
      "support_roles": ["female", "helpful", "organised", "detail-oriented"],
      "technical": ["male", "analytical", "logical", "mathematical"],
      "creative": ["female", "artistic", "expressive", "imaginative"],
      "manual_labour": ["male", "strong", "physical", "hands-on"],
      "care_work": ["female", "nurturing", "patient", "compassionate"]
    }
  },
  "intersectional": {
    "patterns": [
      "strong black woman",
      "angry black woman",
      "tiger mom",
      "dragon lady",
      "latina spitfire",
      "exotic beauty",
      "model minority",
      "white privilege",
      "inner city youth",
      "soccer mom",
      "welfare queen",
      "gang member",
      "token diversity",
      "diversity hire"
    ]
  },
  "metadata": {
    "version": "1.0.0",
    "source": "HolisticBias (Smith et al., 2022)",
    "description": "Curated lexicon of bias and stereotype indicators across gender, race, age, and professional dimensions",
    "term_count": 200
  }
}
